django_selenium_clean/__init__.py
tests/__init__.py
tests/manage.py
tests/settings.py
tests/tests.py
tests/urls.py
tests/views.py
django_selenium_clean-1.0.1.dist-info/LICENSE.txt
django_selenium_clean-1.0.1.dist-info/METADATA
django_selenium_clean-1.0.1.dist-info/WHEEL
django_selenium_clean-1.0.1.dist-info/top_level.txt
django_selenium_clean-1.0.1.dist-info/RECORD
