Metadata-Version: 2.1
Name: django-selenium-clean
Version: 1.0.1
Summary: Write clean Selenium tests in Django
Home-page: https://github.com/aptiko/django-selenium-clean
Author: Antonis Christofides
Author-email: antonis@djangodeployment.com
License: BSD 3-Clause License
Classifier: Development Status :: 4 - Beta
Classifier: Environment :: Console
Classifier: Framework :: Django
Classifier: Intended Audience :: Developers
Classifier: License :: OSI Approved :: BSD License
Classifier: Programming Language :: Python
Classifier: Programming Language :: Python :: 3.9
Classifier: Programming Language :: Python :: 3.10
Classifier: Programming Language :: Python :: 3.11
Classifier: Programming Language :: Python :: 3.12
Classifier: Topic :: Software Development :: Testing
License-File: LICENSE.txt
Requires-Dist: django <6,>=2.2
Requires-Dist: selenium <5,>=3
